LICENSE
MANIFEST.in
README.rst
requirements.txt
setup.py
assistant/__init__.py
assistant/forms.py
assistant/models.py
assistant/search_indexes.py
assistant/settings.py
assistant/tests.py
assistant/tools.py
assistant/urls.py
assistant/views.py
assistant/static/css/app.css
assistant/static/css/bootstrap-theme.css
assistant/static/css/bootstrap-theme.min.css
assistant/static/css/bootstrap.css
assistant/static/css/bootstrap.min.css
assistant/static/fonts/Apache License.txt
assistant/static/fonts/DroidSerif-Bold.ttf
assistant/static/fonts/DroidSerif-BoldItalic.ttf
assistant/static/fonts/DroidSerif-Italic.ttf
assistant/static/fonts/DroidSerif.ttf
assistant/static/fonts/GUST e-foundry License.txt
assistant/static/fonts/LeagueGothic-CondensedItalic.otf
assistant/static/fonts/LeagueGothic-CondensedRegular.otf
assistant/static/fonts/LeagueGothic-Italic.otf
assistant/static/fonts/LeagueGothic-Regular.otf
assistant/static/fonts/SIL Open Font License.txt
assistant/static/fonts/glyphicons-halflings-regular.eot
assistant/static/fonts/glyphicons-halflings-regular.svg
assistant/static/fonts/glyphicons-halflings-regular.ttf
assistant/static/fonts/glyphicons-halflings-regular.woff
assistant/static/fonts/texgyrecursor-bold.otf
assistant/static/fonts/texgyrecursor-bolditalic.otf
assistant/static/fonts/texgyrecursor-italic.otf
assistant/static/fonts/texgyrecursor-regular.otf
assistant/static/images/background.png
assistant/static/js/app.js
assistant/static/js/bootstrap.js
assistant/static/js/bootstrap.min.js
assistant/static/js/jquery.js
assistant/templates/assistant/base.html
assistant/templates/assistant/home.html
assistant/templates/assistant/navigation.html
assistant/templates/assistant/stats.html
assistant/templates/assistant/run/detail.html
assistant/templates/assistant/run/edit.html
assistant/templates/assistant/run/list.html
assistant/templates/assistant/run/run.html
assistant/templates/assistant/test/add.html
assistant/templates/assistant/test/delete.html
django_tests_assistant.egg-info/PKG-INFO
django_tests_assistant.egg-info/SOURCES.txt
django_tests_assistant.egg-info/dependency_links.txt
django_tests_assistant.egg-info/not-zip-safe
django_tests_assistant.egg-info/requires.txt
django_tests_assistant.egg-info/top_level.txt