Metadata-Version: 1.1
Name: django-tests-assistant
Version: 0.2.1
Summary: A tool to help keep track of tests, specially for you - developer.
Home-page: https://github.com/tests-assistant/tests-assistant/
Author: Arun Karunagath
Author-email: the1.arun@gmail.com
License: (AGPL v3+) GNU AFFERO GENERAL PUBLIC LICENSE Version 3 or later
Platform: UNKNOWN
Classifier: Development Status :: 4 - Beta
Classifier: Environment :: Web Environment
Classifier: Framework :: Django
Classifier: Intended Audience :: Developers
Classifier: License :: OSI Approved :: GNU Affero General Public License v3 or later (AGPLv3+)
Classifier: Operating System :: OS Independent
Classifier: Programming Language :: Python
Classifier: Programming Language :: Python :: 2.6
Classifier: Programming Language :: Python :: 2.7
